py_google_trends/__init__.py
py_google_trends/google_trend_request.py
py_google_trends-0.2.2.dist-info/METADATA
py_google_trends-0.2.2.dist-info/WHEEL
py_google_trends-0.2.2.dist-info/top_level.txt
py_google_trends-0.2.2.dist-info/RECORD
