Metadata-Version: 2.1
Name: py-google-trends
Version: 0.2.2
Summary: Simple request wrapper for Google Trends API
Author: wysohn
Author-email: wysohn2002@naver.com
Requires-Python: >=3.6
